[{"name": "TP SAURYA LIMITED", "poolingStationName": "BIKANER-III", "regionCode": "NR"}, {"name": "SOLTOWN INFRA  PRIVATE LIMITED", "poolingStationName": "Bikaner-II", "regionCode": "NR"}, {"name": "Serentica Renewables India Private Ltd", "poolingStationName": "Bikaner-II", "regionCode": "NR"}, {"name": "Hazel Hybren Private Ltd", "poolingStationName": "Bikaner-IV", "regionCode": "NR"}, {"name": "Litsolaire Energy Private Ltd", "poolingStationName": "Bikaner-II", "regionCode": "NR"}, {"name": "Furies Solren Private Ltd", "poolingStationName": "Bikaner-IV", "regionCode": "NR"}, {"name": "ACME Cleantech Solutions Private Limited.", "poolingStationName": "Bikaner-III", "regionCode": "NR"}, {"name": "ALF Solar Amarsar", "poolingStationName": "Bikaner-II", "regionCode": "NR"}, {"name": "IB VOGT SOLAR SEVEN PRIVATE LIMITED(IBVSSPL)", "poolingStationName": "Fatehgarh-III", "regionCode": "NR"}, {"name": "RENEW SAMIR SHAKTI THREE PRIVATE LIMITED", "poolingStationName": "Fatehgarh-III", "regionCode": "NR"}, {"name": "ADANI SOLAR ENERGY BARMER ONE LIMITED(ASEB1L))", "poolingStationName": "Fatehgarh-III", "regionCode": "NR"}, {"name": "Khaba Renewable Energy Private Limited (KREPL)", "poolingStationName": "Fatehgarh-III", "regionCode": "NR"}, {"name": "Juniper Green Stellar Private Limited(JGSPL)", "poolingStationName": "Fatehgarh-IV", "regionCode": "NR"}, {"name": "PROJECT 11 RENEWABLE POWER PRIVATE LIMITED(P11RPPL)", "poolingStationName": "Bhadla-II", "regionCode": "NR"}, {"name": "PROJECT 16 RENEWABLE POWER PRIVATE LIMITED(P16RPPL)", "poolingStationName": "Bhadla-II", "regionCode": "NR"}, {"name": "ACME SUN POWER PRIVATE LIMITED(ASPPL)", "poolingStationName": "Bhadla-II", "regionCode": "NR"}, {"name": "ACME SURYODAYA PRIVATE LIMITED(ACME_SPL)", "poolingStationName": "Fatehgarh-I", "regionCode": "NR"}, {"name": "ACME Surya POWER Private Limited (ASRPPL)", "poolingStationName": "Bikaner-II", "regionCode": "NR"}, {"name": "Clean Max Celestial Private Limited(CMCPL)", "poolingStationName": "Bikaner-II", "regionCode": "NR"}, {"name": "Clean Max Enviro Energy Solutions Limited(CMEESL)", "poolingStationName": "Bikaner-II", "regionCode": "NR"}, {"name": "Energizent POWER Private Limited", "poolingStationName": "Fatehgarh-III", "regionCode": "NR"}, {"name": "BBMB Panipat", "poolingStationName": "Panipat", "regionCode": "NR"}, {"name": "Tehri", "poolingStationName": "Tehri", "regionCode": "NR"}, {"name": "Adani Green Energy Twenty Five B Limited (AGE25BL)", "poolingStationName": "Ramgarh-II", "regionCode": "NR"}, {"name": "Teq Green POWER XVIII Private Limited", "poolingStationName": "Fatehgarh-III", "regionCode": "NR"}, {"name": "Renew Solar Shakti Five Private Limited", "poolingStationName": "Fatehgarh-III", "regionCode": "NR"}, {"name": "AMPIN ENERGY GREEN TEN PRIVATE LIMITED(AEG10PL)", "poolingStationName": "Fatehgarh-IV", "regionCode": "NR"}, {"name": "HRP Green POWER Private Limited", "poolingStationName": "Bhadla-III", "regionCode": "NR"}, {"name": "Aditya Birla Renewables subsdiary Ltd", "poolingStationName": "Fatehgarh-III", "regionCode": "NR"}, {"name": "Serentica Renewables India 9 Private Limited (SRI9PL)", "poolingStationName": "Fatehgarh-III", "regionCode": "NR"}, {"name": "SERENTICA RENEWABLES INDIA 8 PRIVATE LIMITED (SRI8PL)", "poolingStationName": "Fatehgarh_III", "regionCode": "NR"}, {"name": "JUNIPER GREEN ENERGY LIMITED(Ran JGEPL)", "poolingStationName": "Jamkhambaliya", "regionCode": "WR"}, {"name": "MOUNTING RENEWABLE POWER LIMITED(Tebhada )", "poolingStationName": "Jamkhambaliya", "regionCode": "WR"}, {"name": "GUJARAT INDUSTRIES POWER   COMPANY LTD (SPD: SAEL, COAL   INDIA)(GIPCL PSS1)", "poolingStationName": "Khavda-2 PS", "regionCode": "WR"}, {"name": "GUJARAT INDUSTRIES POWER   COMPANY LTD(GIPCL PSS2)", "poolingStationName": "Khavda-2 PS", "regionCode": "WR"}, {"name": "AIRPOWER WINDFARMS PRIVATE LIMITED(Sidhpur)", "poolingStationName": "Jamkhambaliya", "regionCode": "WR"}, {"name": "NTPC RENEWABLE ENERGY   LIMITED(Vanki Devsar)", "poolingStationName": "Bhuj PS", "regionCode": "WR"}, {"name": "NTPC RENEWABLE ENERGY   LIMITED(Jamjhodpur)", "poolingStationName": "Jamhambaliya", "regionCode": "WR"}, {"name": "INDIANOIL NTPC GREEN ENERGY PRIVATE LIMITED(Manja)", "poolingStationName": "Jamkhambaliya", "regionCode": "WR"}, {"name": "NTPC RENEWABLE ENERGY   LIMITED(NTPC REL PSS4)", "poolingStationName": "Khavda-2 PS", "regionCode": "WR"}, {"name": "VEH JAYIN RENEWABLES PRIVATE LIMITED(Dhar)", "poolingStationName": "Rajgarh PG", "regionCode": "WR"}, {"name": "Adani Green Energy Limited(KPSS7)", "poolingStationName": "Khavda-1 PS", "regionCode": "WR"}, {"name": "ADANI GREEN ENERGY THIRTY TWO LIMITED(Mandovi)", "poolingStationName": "Bhuj-II PS", "regionCode": "WR"}, {"name": "ADANI WIND ENERGY KUTCHH THREE LIMITED(Adani Mundra PSS)", "poolingStationName": "Interim LILO of 400 kV CGPL-Jetpur ckt", "regionCode": "WR"}, {"name": "Adani Green Energy Limited(KPSS 11)", "poolingStationName": "Khavda-3 PS", "regionCode": "WR"}, {"name": "Adani Green Energy Limited(KPSS 12)", "poolingStationName": "Khavda-3 PS", "regionCode": "WR"}, {"name": "ADANI RENEWABLE ENERGY   EIGHT LIMITED(Ludbay)", "poolingStationName": "Bhuj-II PS", "regionCode": "WR"}, {"name": "Abnergia Renewable Private Limited (ARPL) / Oyster RENEWABLE ENERGY PVT LTD(Agar Malwa)", "poolingStationName": "Pachora PS", "regionCode": "WR"}, {"name": "TATA POWER RENEWABLE ENERGY LIMITED(Borkhed)", "poolingStationName": "Kallam PS", "regionCode": "WR"}, {"name": "SPRING VAYU VIDYUT PRIVATE   LIMITED(Bharadwa)", "poolingStationName": "Radhanesda PS", "regionCode": "WR"}, {"name": "Sprng Vayu Vidyut Private Limited(Hajaratpur)", "poolingStationName": "Rajgarh PG", "regionCode": "WR"}, {"name": "Sprng Power Earth Pvt. Ltd. (SPEPL)(Padan)", "poolingStationName": "Radhanesda PS", "regionCode": "WR"}, {"name": "Serentica Renewables India Private Limited(Konhali)", "poolingStationName": "Solapur PG", "regionCode": "WR"}, {"name": "Serentica Renewables India Private Limited(Dahiphal)", "poolingStationName": "Kallam PS", "regionCode": "WR"}, {"name": "ReNew Samir Urja Private Limited & Renew Urja Sanchar Ltd(Badnagar)", "poolingStationName": "Indore PG", "regionCode": "WR"}, {"name": "NHPC(NHPC PSS-1)", "poolingStationName": "Khavda-3 PS", "regionCode": "WR"}, {"name": "Skadar Solar Pvt. Ltd.(Skadar Solar Pvt. Ltd.)", "poolingStationName": "Solapur PS", "regionCode": "WR"}, {"name": "SOLARCRAFT POWER INDIA 16 PRIVATE LIMITED(Gulbarga)", "poolingStationName": "Solapur PS", "regionCode": "WR"}, {"name": "Avaada Energy Private Limited(Avaada Energy Private Limited)", "poolingStationName": "Jamkhambaliya", "regionCode": "WR"}, {"name": "NTPC REL(Samanda)", "poolingStationName": "Bhuj-II PS", "regionCode": "WR"}, {"name": "ACME CLEANTECH SOLUTIONS PRIVATE LIMITED(ACME_Pachora)", "poolingStationName": "Pachora PS", "regionCode": "WR"}, {"name": "ACME CLEANTECH SOLUTIONS PRIVATE LIMITED(Kharnai)", "poolingStationName": "Neemach", "regionCode": "WR"}, {"name": "HEXA CLIMATE SOLUTIONS PRIVATE LIMITE   (Baranda)", "poolingStationName": "Bhuj PS", "regionCode": "WR"}, {"name": "AGE26AL Khavda PSS6", "poolingStationName": "KPS1", "regionCode": "WR"}, {"name": "ASEJ6PL Khavda PSS8", "poolingStationName": "KPS3", "regionCode": "WR"}, {"name": "AGE25CL Khavda PSS8", "poolingStationName": "KPS3", "regionCode": "WR"}, {"name": "AGE24L SRPL Khavda PSS10", "poolingStationName": "KPS3", "regionCode": "WR"}, {"name": "AGE24L Khavda PSS5", "poolingStationName": "KPS1", "regionCode": "WR"}, {"name": "AGE26BL Khavda PSS10", "poolingStationName": "KPS3", "regionCode": "WR"}, {"name": "ARE43L BESS - SRPL Khavda PSS10", "poolingStationName": "KPS3", "regionCode": "WR"}, {"name": "AGE26AL - SRPL Khavda PSS12", "poolingStationName": "KPS3", "regionCode": "WR"}, {"name": "ARE37L BESS - AGEL Khavda PSS5", "poolingStationName": "KPS1", "regionCode": "WR"}, {"name": "Renew Green MHS One Pvt Ltd - RGESPL PSS-1", "poolingStationName": "Solapur", "regionCode": "WR"}, {"name": "Avaada GJ Sustainable Private Limited", "poolingStationName": "Lakadiya", "regionCode": "WR"}, {"name": "Veh Saurya Urja Pvt Ltd", "poolingStationName": "Pachora", "regionCode": "WR"}, {"name": "Oyster Green Hybrid One Pvt Ltd", "poolingStationName": "Pachora", "regionCode": "WR"}, {"name": "Juniper Green Energy Limited", "poolingStationName": "Jam Khambhaliya", "regionCode": "WR"}, {"name": "Sprng Akshay Urja Pvt Ltd", "poolingStationName": "Rajgarh", "regionCode": "WR"}, {"name": "TEQ Green Power XI Pvt Ltd", "poolingStationName": "Kallam", "regionCode": "WR"}, {"name": "Ayana Power Four Private Limited at Devasar", "poolingStationName": "Bhuj", "regionCode": "WR"}, {"name": "Ayana Power Four Private Limited at Zura", "poolingStationName": "Bhuj", "regionCode": "WR"}, {"name": "NTPC REL Khavda PSS2", "poolingStationName": "KPS2", "regionCode": "WR"}, {"name": "NTPC REL Khavda PSS1", "poolingStationName": "KPS3", "regionCode": "WR"}, {"name": "NTPC REL Vanki", "poolingStationName": "Bhuj", "regionCode": "WR"}, {"name": "Coal India Limited at GIPCL", "poolingStationName": "KPS2", "regionCode": "WR"}, {"name": "NTPC REL at GSECL", "poolingStationName": "KPS2", "regionCode": "WR"}, {"name": "Engie Energy India Pvt Ltd at GSECL", "poolingStationName": "KPS2", "regionCode": "WR"}, {"name": "JSW Renew Energy Ten Ltd at GSECL", "poolingStationName": "KPS2", "regionCode": "WR"}, {"name": "Mounting Renewable Power Ltd", "poolingStationName": "Jam Khambhaliya", "regionCode": "WR"}, {"name": "Serentica Renewables India4 Pvt Ltd", "poolingStationName": "Kallam", "regionCode": "WR"}, {"name": "Airpower Windfarms Pvt Ltd", "poolingStationName": "Jam Khambhaliya", "regionCode": "WR"}, {"name": "Oyster Green Hybrid One Pvt Ltd at Dayapar", "poolingStationName": "Bhuj", "regionCode": "WR"}, {"name": "ARE36L BESS - AGEL Khavda PSS8", "poolingStationName": "KPS3", "regionCode": "WR"}, {"name": "AGE25CL Khavda PSS14", "poolingStationName": "KPS3", "regionCode": "WR"}, {"name": "AGE26AL Khavda PSS14", "poolingStationName": "KPS3", "regionCode": "WR"}, {"name": "NTPC REL at Jamjodhpur", "poolingStationName": "Jam Khambhaliya", "regionCode": "WR"}, {"name": "Veh Jayin Renewables Private Limited", "poolingStationName": "Rajgarh", "regionCode": "WR"}, {"name": "Continuum Power Trading (TN) Private Limited", "poolingStationName": "Bhuj", "regionCode": "WR"}, {"name": "Aditya Birla Renewable Energy Limited (ABREL) Valsara", "poolingStationName": "Bhuj-II", "regionCode": "WR"}, {"name": "Waree Energies Limited", "poolingStationName": "Rewa", "regionCode": "WR"}, {"name": "Sprng Vayu Vidyut Pvt Ltd", "poolingStationName": "Rajgarh", "regionCode": "WR"}, {"name": "NTPC REL Khavda PSS4", "poolingStationName": "KPS2", "regionCode": "WR"}, {"name": "APSEZ Khavda PSS4", "poolingStationName": "KPS1", "regionCode": "WR"}, {"name": "ARE57L PSS13", "poolingStationName": "KPS1", "regionCode": "WR"}, {"name": "IndianOil NTPC Green Energy Limited (INGEL)", "poolingStationName": "Jam Khambhaliya", "regionCode": "WR"}, {"name": "ACL Khavda PSS4", "poolingStationName": "KPS1", "regionCode": "WR"}, {"name": "ARE41L Khavda PSS4", "poolingStationName": "KPS1", "regionCode": "WR"}, {"name": "AHEJ5L Khavda PSS8", "poolingStationName": "KPS3", "regionCode": "WR"}, {"name": "NHPC NP Kunta", "poolingStationName": "NP Kunta", "regionCode": "SR"}, {"name": "AMPIN", "poolingStationName": "Kurnool-III", "regionCode": "SR"}, {"name": "KSPDCL", "poolingStationName": "Pavagada", "regionCode": "SR"}, {"name": "ReNew Vikram Shakti Pvt Ltd", "poolingStationName": "Ananthapuram", "regionCode": "SR"}, {"name": "M/s SolarXL Beta Energy Pvt Ltd.(HEXA)", "poolingStationName": "Gadag-II", "regionCode": "SR"}, {"name": "JINDAL GREEN WIND 1 PRIVATE LIMITED", "poolingStationName": "Koppal-II", "regionCode": "SR"}, {"name": "PROJECT NINE RENEWABLE POWER PRIVATE LIMITED", "poolingStationName": "Ananthapuram PS", "regionCode": "SR"}, {"name": "Ayana Renewable POWER Four Pvt. Ltd.", "poolingStationName": "Ananthapuram PS", "regionCode": "SR"}, {"name": "JSW_270", "poolingStationName": "Karur", "regionCode": "SR"}, {"name": "Hero Solar Energy Pvt. Ltd.", "poolingStationName": "Kurnool-III", "regionCode": "SR"}, {"name": "SECI", "poolingStationName": "Pavagada", "regionCode": "SR"}, {"name": "TPREL", "poolingStationName": "Koppal-II", "regionCode": "SR"}, {"name": "Veh Green Energy Private Limited", "poolingStationName": "Koppal-II", "regionCode": "SR"}, {"name": "JSW_140", "poolingStationName": "Tuticorin-II", "regionCode": "SR"}, {"name": "JSW_Neo", "poolingStationName": "Karur", "regionCode": "SR"}, {"name": "M/s Adani Renewable energy Forty two Pvt. Ltd", "poolingStationName": "Kurnool-III", "regionCode": "SR"}, {"name": "M/s Gadag Power India Private Limited", "poolingStationName": "Koppal-II", "regionCode": "SR"}, {"name": "UPC RENEWABLES INDIA MANAGEMENT PRIVATE LIMITED", "poolingStationName": "Bijapur S/S", "regionCode": "SR"}, {"name": "SAEL Solar MHP2 Pvt Ltd", "poolingStationName": "Kurnool-III", "regionCode": "SR"}, {"name": "Sembcorp Green Infra Pvt. Ltd.", "poolingStationName": "Gadag", "regionCode": "SR"}, {"name": "JSW Renew Energy Limited", "poolingStationName": "Karur", "regionCode": "SR"}, {"name": "NTPC Ramagundam (176MW)", "poolingStationName": "Ramagundam", "regionCode": "SR"}, {"name": "Serentica Renewables India 1 Private Limited", "poolingStationName": "Koppal", "regionCode": "SR"}, {"name": "Serentica Renewables India 3 Private Limited", "poolingStationName": "Gadag", "regionCode": "SR"}, {"name": "Greenko AP01 IREP Pvt Ltd", "poolingStationName": "Kurnool", "regionCode": "SR"}, {"name": "Zenataris Renewable Energy Private Limited", "poolingStationName": "Hiriyur", "regionCode": "SR"}, {"name": "IRCON RENEWABLE POWER LIMITED", "poolingStationName": "PAVAGADA", "regionCode": "SR"}, {"name": "AHEJOL_W", "poolingStationName": "Fatehgarh2", "regionCode": "NR"}, {"name": "AHEJ2L_W", "poolingStationName": "Fatehgarh2", "regionCode": "NR"}, {"name": "AHEJ3L_W", "poolingStationName": "Fatehgarh2", "regionCode": "NR"}, {"name": "ASEJOPL_W_FTG2", "poolingStationName": "Fatehgarh2", "regionCode": "NR"}, {"name": "AHEJ4L_W", "poolingStationName": "Fatehgarh1", "regionCode": "NR"}, {"name": "AEG08_W_FTG4", "poolingStationName": "Fatehgarh4", "regionCode": "NR"}, {"name": "AEG03_W_FTG4", "poolingStationName": "Fatehgarh4", "regionCode": "NR"}, {"name": "AEG10_W_FTG4", "poolingStationName": "Fatehgarh4", "regionCode": "NR"}, {"name": "Bhadla Adani Azure Power", "poolingStationName": "Bhadla", "regionCode": "NR"}, {"name": "Bhadla Clean Solar Power", "poolingStationName": "Bhadla", "regionCode": "NR"}, {"name": "Bhadla Soft Bank Power", "poolingStationName": "Bhadla", "regionCode": "NR"}, {"name": "Acme Power-SOLAR", "poolingStationName": "Bhadla", "regionCode": "NR"}, {"name": "Azure Power Thirty Four", "poolingStationName": "Bhadla", "regionCode": "NR"}, {"name": "Tata Power Renewable Ene", "poolingStationName": "Bhadla", "regionCode": "NR"}, {"name": "Bhadla Adani Renew Power", "poolingStationName": "Bhadla", "regionCode": "NR"}, {"name": "ASE4PL", "poolingStationName": "Bhadla", "regionCode": "NR"}, {"name": "ARERJL", "poolingStationName": "Bhadla", "regionCode": "NR"}, {"name": "ASEJ2L", "poolingStationName": "Bhadla", "regionCode": "NR"}, {"name": "Mahindra Renewables Pvt", "poolingStationName": "Bhadla", "regionCode": "NR"}, {"name": "SBE6PL", "poolingStationName": "Bhadla", "regionCode": "NR"}, {"name": "AP41PL_BHDL", "poolingStationName": "Bhadla", "regionCode": "NR"}, {"name": "APMPL_BHDL", "poolingStationName": "Bhadla", "regionCode": "NR"}, {"name": "CSPJPL_BHDL", "poolingStationName": "Bhadla", "regionCode": "NR"}, {"name": "ASERJ2PL_BHDL", "poolingStationName": "Bhadla", "regionCode": "NR"}, {"name": "ACL_BHDL", "poolingStationName": "Bhadla", "regionCode": "NR"}, {"name": "Renew Power-SOLAR", "poolingStationName": "Bikaner", "regionCode": "NR"}, {"name": "Azure Power Forty Three", "poolingStationName": "Bikaner", "regionCode": "NR"}, {"name": "SBSRPC11PL_BKN", "poolingStationName": "Bikaner", "regionCode": "NR"}, {"name": "ASunceEPL_BKN", "poolingStationName": "Bikaner", "regionCode": "NR"}, {"name": "ARP1PL_BKN", "poolingStationName": "Bikaner", "regionCode": "NR"}, {"name": "AvRJHNPL_BKN", "poolingStationName": "Bikaner", "regionCode": "NR"}, {"name": "AvSusRJPPL_BKN", "poolingStationName": "Bikaner", "regionCode": "NR"}, {"name": "RSRPL_BKN", "poolingStationName": "Bikaner", "regionCode": "NR"}, {"name": "TS1PL_BKN", "poolingStationName": "Bikaner", "regionCode": "NR"}, {"name": "TPGEL_BKN", "poolingStationName": "Bikaner", "regionCode": "NR"}, {"name": "TPSL_BKN", "poolingStationName": "Bikaner", "regionCode": "NR"}, {"name": "ARP3PL_BKN", "poolingStationName": "Bikaner", "regionCode": "NR"}, {"name": "Singrauli-SOLAR", "poolingStationName": "Singrauli", "regionCode": "NR"}, {"name": "Unchahar-SOLAR", "poolingStationName": "Unchahar", "regionCode": "NR"}, {"name": "Dadri-SOLAR", "poolingStationName": "Dadri", "regionCode": "NR"}, {"name": "Auraiya-SOLAR", "poolingStationName": "Auraiya", "regionCode": "NR"}, {"name": "Anta-Solar", "poolingStationName": "Anta", "regionCode": "NR"}, {"name": "AHEJOL", "poolingStationName": "Fatehgarh2", "regionCode": "NR"}, {"name": "ERCPL_FTG2", "poolingStationName": "Fatehgarh2", "regionCode": "NR"}, {"name": "RSWPL3_FTG2", "poolingStationName": "Fatehgarh2", "regionCode": "NR"}, {"name": "RSEJ3PL_FTG2", "poolingStationName": "Fatehgarh2", "regionCode": "NR"}, {"name": "AHEJ2L_S_FTG2", "poolingStationName": "Fatehgarh2", "regionCode": "NR"}, {"name": "AHEJ3L_S_FTG2", "poolingStationName": "Fatehgarh2", "regionCode": "NR"}, {"name": "RSBPL_FTG2", "poolingStationName": "Fatehgarh2", "regionCode": "NR"}, {"name": "RSUPL_FTG2", "poolingStationName": "Fatehgarh2", "regionCode": "NR"}, {"name": "ASEJOPL_S_FTG2", "poolingStationName": "Fatehgarh2", "regionCode": "NR"}, {"name": "DSNTPC_FTG2", "poolingStationName": "Fatehgarh2", "regionCode": "NR"}, {"name": "ASERJ2PL_FTG2", "poolingStationName": "Fatehgarh2", "regionCode": "NR"}, {"name": "AGE24L", "poolingStationName": "Fatehgarh2", "regionCode": "NR"}, {"name": "AHEJ4L_S_FTG1", "poolingStationName": "Fatehgarh1", "regionCode": "NR"}, {"name": "NSNTPC_FTG1", "poolingStationName": "Fatehgarh1", "regionCode": "NR"}, {"name": "ADSPPL_FTG_INF", "poolingStationName": "Fatehgarh1", "regionCode": "NR"}, {"name": "ADSEPL_FTG_INF", "poolingStationName": "Fatehgarh1", "regionCode": "NR"}, {"name": "ARSEPL_FTG_INF", "poolingStationName": "Fatehgarh1", "regionCode": "NR"}, {"name": "ADPPL_FTG_INF", "poolingStationName": "Fatehgarh1", "regionCode": "NR"}, {"name": "AcHPPL_BHDL2", "poolingStationName": "Bhadla2", "regionCode": "NR"}, {"name": "ABCREPL_BHDL2", "poolingStationName": "Bhadla2", "regionCode": "NR"}, {"name": "MSUPL_BHDL2", "poolingStationName": "Bhadla2", "regionCode": "NR"}, {"name": "KSPPNL_BHDL2", "poolingStationName": "Bhadla2", "regionCode": "NR"}, {"name": "ASEPL", "poolingStationName": "Bhadla2", "regionCode": "NR"}, {"name": "NOKHRANT_BHDL2", "poolingStationName": "Bhadla2", "regionCode": "NR"}, {"name": "RSEKPL_BHDL2", "poolingStationName": "Bhadla2", "regionCode": "NR"}, {"name": "AEGSPL_BHDL2", "poolingStationName": "Bhadla2", "regionCode": "NR"}, {"name": "AEGFPL_BHDL2", "poolingStationName": "Bhadla2", "regionCode": "NR"}, {"name": "AGE25L_BHD2", "poolingStationName": "Bhadla2", "regionCode": "NR"}, {"name": "AEG4PL_BHD2", "poolingStationName": "Bhadla2", "regionCode": "NR"}, {"name": "GSPL_BHD2", "poolingStationName": "Bhadla2", "regionCode": "NR"}, {"name": "NOKH_BHD2", "poolingStationName": "Bhadla2", "regionCode": "NR"}, {"name": "ERAPL_BHD2", "poolingStationName": "Bhadla2", "regionCode": "NR"}, {"name": "ASEJ6PL_BHD2", "poolingStationName": "Bhadla2", "regionCode": "NR"}, {"name": "AXPPL_FTG3", "poolingStationName": "Fatehgarh3", "regionCode": "NR"}, {"name": "RSVPL_FTG3", "poolingStationName": "Fatehgarh3", "regionCode": "NR"}, {"name": "RSPPL_FTG3", "poolingStationName": "Fatehgarh3", "regionCode": "NR"}, {"name": "RSRPL_FTG3", "poolingStationName": "Fatehgarh3", "regionCode": "NR"}, {"name": "RSAPL_FTG3", "poolingStationName": "Fatehgarh3", "regionCode": "NR"}, {"name": "NRSVPL_FTG3", "poolingStationName": "Fatehgarh3", "regionCode": "NR"}, {"name": "RSJPL_FTG3", "poolingStationName": "Fatehgarh3", "regionCode": "NR"}, {"name": "XXPPL_FTG3", "poolingStationName": "Fatehgarh3", "regionCode": "NR"}, {"name": "ABCRJ02_FTG3", "poolingStationName": "Fatehgarh3", "regionCode": "NR"}, {"name": "EPPL_FTG3", "poolingStationName": "Fatehgarh3", "regionCode": "NR"}, {"name": "RSSPL_FTG3", "poolingStationName": "Fatehgarh3", "regionCode": "NR"}, {"name": "RSS3PL_FTG3", "poolingStationName": "Fatehgarh3", "regionCode": "NR"}, {"name": "KHRPL_FTG3", "poolingStationName": "Fatehgarh3", "regionCode": "NR"}, {"name": "ASEB1L_FTG3", "poolingStationName": "Fatehgarh3", "regionCode": "NR"}, {"name": "IBVS7PL_FTG3", "poolingStationName": "Fatehgarh3", "regionCode": "NR"}, {"name": "AAPL_BKN2", "poolingStationName": "Bikaner 2", "regionCode": "NR"}, {"name": "GEPL_BKN2", "poolingStationName": "Bikaner 2", "regionCode": "NR"}, {"name": "OVEPL_BKN2", "poolingStationName": "Bikaner 2", "regionCode": "NR"}, {"name": "ARTPL_BKN2", "poolingStationName": "Bikaner 2", "regionCode": "NR"}, {"name": "TESPL_BKN2", "poolingStationName": "Bikaner 2", "regionCode": "NR"}, {"name": "TPSL_BKN2", "poolingStationName": "Bikaner 2", "regionCode": "NR"}, {"name": "TGEPL_BKN2", "poolingStationName": "Bikaner 2", "regionCode": "NR"}, {"name": "TSESPL_BKN2", "poolingStationName": "Bikaner 2", "regionCode": "NR"}, {"name": "SR14PL_BKN2", "poolingStationName": "Bikaner 2", "regionCode": "NR"}, {"name": "TSESOPL_BKN2", "poolingStationName": "Bikaner 2", "regionCode": "NR"}, {"name": "SR15PL_BKN2", "poolingStationName": "Bikaner 2", "regionCode": "NR"}, {"name": "JGCPL_BKN2", "poolingStationName": "Bikaner 2", "regionCode": "NR"}, {"name": "TCSPL_BKNR2", "poolingStationName": "Bikaner 2", "regionCode": "NR"}, {"name": "JNEPL_BKN2", "poolingStationName": "Bikaner 2", "regionCode": "NR"}, {"name": "SGEPL_BKNR2", "poolingStationName": "Bikaner 2", "regionCode": "NR"}, {"name": "KBNHPC_BKN2", "poolingStationName": "Bikaner 2", "regionCode": "NR"}, {"name": "ASSPL_BKNR2", "poolingStationName": "Bikaner 2", "regionCode": "NR"}, {"name": "KREPL_BKN2", "poolingStationName": "Bikaner 2", "regionCode": "NR"}, {"name": "JREPL_BKN2", "poolingStationName": "Bikaner 2", "regionCode": "NR"}, {"name": "RDUPL_BKN2", "poolingStationName": "Bikaner 2", "regionCode": "NR"}, {"name": "AEG08_S_FTG4", "poolingStationName": "Fatehgarh4", "regionCode": "NR"}, {"name": "AEG03_S_FTG4", "poolingStationName": "Fatehgarh4", "regionCode": "NR"}, {"name": "AEG10_S_FTG4", "poolingStationName": "Fatehgarh4", "regionCode": "NR"}, {"name": "JGSPL_S_FTG4", "poolingStationName": "Fatehgarh4", "regionCode": "NR"}, {"name": "BHISOL_BB", "poolingStationName": "BBMB", "regionCode": "NR"}, {"name": "HISOL_BB", "poolingStationName": "Haryana", "regionCode": "NR"}, {"name": "HRPGP_BHDL3", "poolingStationName": "Bhadla3", "regionCode": "NR"}, {"name": "AGE25BL_RMGRH", "poolingStationName": "Ramgarh", "regionCode": "NR"}, {"name": "OKWPL Ostro Kutch_Bachau", "poolingStationName": "Bachau", "regionCode": "WR"}, {"name": "Renew (Bhuvad)_Bachau", "poolingStationName": "Bachau", "regionCode": "WR"}, {"name": "OEPL_Bachau", "poolingStationName": "Bachau", "regionCode": "WR"}, {"name": "GIWEL-2(Vadva)_Bhuj", "poolingStationName": "Bhuj", "regionCode": "WR"}, {"name": "GIWEL-3 (Naranpar)_Bhuj", "poolingStationName": "Bhuj", "regionCode": "WR"}, {"name": "Inox (Dayapar)_Bhuj", "poolingStationName": "Bhuj", "regionCode": "WR"}, {"name": "AWEK1L_Bhuj", "poolingStationName": "Bhuj", "regionCode": "WR"}, {"name": "Alfanar (Nana Valka)_Bhuj", "poolingStationName": "Bhuj", "regionCode": "WR"}, {"name": "Renew(AP2) (Gadhsisa)_Bhuj", "poolingStationName": "Bhuj", "regionCode": "WR"}, {"name": "AWEKFL (Ratadiya)_Bhuj", "poolingStationName": "Bhuj", "regionCode": "WR"}, {"name": "CPTTNPL (Dayapar)_Bhuj", "poolingStationName": "Bhuj", "regionCode": "WR"}, {"name": "ASIPL (Baranda)_Bhuj", "poolingStationName": "Bhuj", "regionCode": "WR"}, {"name": "Alfa Netra Vayu (Kota Madh)_Bhuj", "poolingStationName": "Bhuj", "regionCode": "WR"}, {"name": "NTPC Renewable energy limited", "poolingStationName": "Bhuj", "regionCode": "WR"}, {"name": "AyanaRP4_DVSR_BHJ_HW", "poolingStationName": "Bhuj", "regionCode": "WR"}, {"name": "Srijan_Bhuj_2", "poolingStationName": "Bhuj_2", "regionCode": "WR"}, {"name": "Sitac_Bhuj_2", "poolingStationName": "Bhuj_2", "regionCode": "WR"}, {"name": "AWEK4L_Dedya_Bhuj_2", "poolingStationName": "Bhuj_2", "regionCode": "WR"}, {"name": "CGERP_MORJAR_BHJ2_HW", "poolingStationName": "Bhuj_2", "regionCode": "WR"}, {"name": "POWERICA_Jamkhambhalia", "poolingStationName": "Jamkhambhalia", "regionCode": "WR"}, {"name": "Apraava(AEPL)_Jamkhambhalia (Khakarda)", "poolingStationName": "Jamkhambhalia", "regionCode": "WR"}, {"name": "Torrent Solargen (Sidpur)", "poolingStationName": "Jamkhambhalia", "regionCode": "WR"}, {"name": "Adani_Wind(SBESS)_IndorePG", "poolingStationName": "Indore", "regionCode": "WR"}, {"name": "ARE41L_PSS3_KPS1_W", "poolingStationName": "Khavda", "regionCode": "WR"}, {"name": "ARE41L_PSS13_KPS1_W", "poolingStationName": "Khavda", "regionCode": "WR"}, {"name": "ACL_PSS4_KPS1_W", "poolingStationName": "Khavda", "regionCode": "WR"}, {"name": "ARE41L_PSS4_KPS1_W", "poolingStationName": "Khavda", "regionCode": "WR"}, {"name": "APSEZ_PSS4_KPS1_W", "poolingStationName": "Khavda", "regionCode": "WR"}, {"name": "AHEJ5L_PSS4_KPS1_W", "poolingStationName": "Khavda", "regionCode": "WR"}, {"name": "AGE25BL_PSS9_KPS1_HW", "poolingStationName": "Khavda", "regionCode": "WR"}, {"name": "AGE24L_PSS4_KPS1_W", "poolingStationName": "Khavda", "regionCode": "WR"}, {"name": "AGE26BL_PSS10_KPS1_W", "poolingStationName": "Khavda", "regionCode": "WR"}, {"name": "ARE55L_PSS3_KPS1_HW", "poolingStationName": "Khavda", "regionCode": "WR"}, {"name": "AHEJ5L_PSS5_KPS1_W", "poolingStationName": "Khavda", "regionCode": "WR"}, {"name": "AHEJ5L_PSS8_KPS3_HW", "poolingStationName": "Khavda Pooling_3", "regionCode": "WR"}, {"name": "ARE3L_PSS8_KPS3_HW", "poolingStationName": "Gujarat", "regionCode": "WR"}, {"name": "RSRPL_GHTND_klm_W", "poolingStationName": "Kallam Pooling", "regionCode": "WR"}, {"name": "BlueLeaf_CP_PCHR_HW", "poolingStationName": "Pachora Pooling", "regionCode": "WR"}, {"name": "RGMHS1_TLJPR_SLPR_HW", "poolingStationName": "Solapur PG Pooling", "regionCode": "WR"}, {"name": "Arinsun (Barsaitadesh)_Rewa", "poolingStationName": "Rewa Pooling", "regionCode": "WR"}, {"name": "Acme (Ramnagar)_Rewa", "poolingStationName": "Rewa Pooling", "regionCode": "WR"}, {"name": "Mahindra (Badwar)_Rewa", "poolingStationName": "Rewa Pooling", "regionCode": "WR"}, {"name": "TPREL_RSP", "poolingStationName": "Radhaneshda", "regionCode": "WR"}, {"name": "GIPCL_RSP", "poolingStationName": "Radhaneshda", "regionCode": "WR"}, {"name": "ESPL_RSP", "poolingStationName": "Radhaneshda", "regionCode": "WR"}, {"name": "GSECL_RSP", "poolingStationName": "Radhaneshda", "regionCode": "WR"}, {"name": "GSECL_ph2_RSP_S", "poolingStationName": "Radhaneshda", "regionCode": "WR"}, {"name": "SJVN Green Energy Limited", "poolingStationName": "Radhaneshda", "regionCode": "WR"}, {"name": "KAWAS", "poolingStationName": "KAWAS Pooling", "regionCode": "WR"}, {"name": "GANDHAR", "poolingStationName": "GANDHAR Pooling", "regionCode": "WR"}, {"name": "Sherisha Raipur", "poolingStationName": "Raipur Pooling", "regionCode": "WR"}, {"name": "Solapur Solar", "poolingStationName": "Solapur NTPC Pooling", "regionCode": "WR"}, {"name": "Masaya  Solar (UPC) Solar project at Khandwa PS-SECI", "poolingStationName": "Khandwa", "regionCode": "WR"}, {"name": "Adani Renewable Energy holding Four limited Solar", "poolingStationName": "Khavda", "regionCode": "WR"}, {"name": "AGE25BL_PSS2_KPS1_SI", "poolingStationName": "Khavda", "regionCode": "WR"}, {"name": "AGE26BL_PSS2_KPS1_SI", "poolingStationName": "Khavda", "regionCode": "WR"}, {"name": "AGE25AL_PSS2_KPS1_SI", "poolingStationName": "Khavda", "regionCode": "WR"}, {"name": "AGE26AL_PSS3_KPS1_SI", "poolingStationName": "Khavda", "regionCode": "WR"}, {"name": "ARE55L_PSS3_KPS1_SI", "poolingStationName": "Khavda", "regionCode": "WR"}, {"name": "ACL_PSS3_KPS1_S", "poolingStationName": "Khavda", "regionCode": "WR"}, {"name": "ARE55L_PSS3_KPS1_HS", "poolingStationName": "Khavda", "regionCode": "WR"}, {"name": "AGE24AL_PSS3_KPS1_S", "poolingStationName": "Khavda", "regionCode": "WR"}, {"name": "ARE57L_PSS13_KPS1_S", "poolingStationName": "Khavda", "regionCode": "WR"}, {"name": "ARE56L_PSS9_KPS1_S", "poolingStationName": "Khavda", "regionCode": "WR"}, {"name": "ARE56L_PSS4_KPS1_S", "poolingStationName": "Khavda", "regionCode": "WR"}, {"name": "ARE45L_PSS5_KPS1_S", "poolingStationName": "Khavda", "regionCode": "WR"}, {"name": "ARE56L_PSS10_KPS1_S", "poolingStationName": "Khavda", "regionCode": "WR"}, {"name": "AHEJ5L_PSS5_KPS1_S", "poolingStationName": "Khavda", "regionCode": "WR"}, {"name": "APSEZ_PSS3_KPS1_S", "poolingStationName": "Khavda", "regionCode": "WR"}, {"name": "AGE26BL_PSS10_KPS1_HS", "poolingStationName": "Khavda", "regionCode": "WR"}, {"name": "BEEMPOW_AGAR_RUM_S", "poolingStationName": "Pachora", "regionCode": "WR"}, {"name": "AVAADA_AGAR_RUM_S", "poolingStationName": "Pachora", "regionCode": "WR"}, {"name": "NTPC_REL_SJPR_RUMS_S", "poolingStationName": "Pachora", "regionCode": "WR"}, {"name": "NTPC_REL1_SJPR_RUMS_S", "poolingStationName": "Pachora", "regionCode": "WR"}, {"name": "TALTUTAI_SJPR_RUMS_S", "poolingStationName": "Pachora", "regionCode": "WR"}, {"name": "BlueLeaf_CP_PCHR_S", "poolingStationName": "Pachora", "regionCode": "WR"}, {"name": "TPSOURY_KWAI_NMCH_S", "poolingStationName": "Neemuch", "regionCode": "WR"}, {"name": "TPSOURY_BRVD_NMCH_S", "poolingStationName": "Neemuch", "regionCode": "WR"}, {"name": "RenewGreenTN3_SLPR_S", "poolingStationName": "Solapur", "regionCode": "WR"}, {"name": "RGMHS3_PSS5_SLPR_S", "poolingStationName": "Solapur", "regionCode": "WR"}, {"name": "NTPCREL_PSS2_KPS2_S", "poolingStationName": "Khavda Pooling 2", "regionCode": "WR"}, {"name": "GIPCL_PSS1_KPS2_S", "poolingStationName": "Khavda Pooling 2", "regionCode": "WR"}, {"name": "KPIG_GSECLS_KPS2_S", "poolingStationName": "Khavda Pooling 2", "regionCode": "WR"}, {"name": "SAELP4_GSECLS_KPS2_S", "poolingStationName": "Khavda Pooling 2", "regionCode": "WR"}, {"name": "SAELP5_GSECLS_KPS2_S", "poolingStationName": "Khavda Pooling 2", "regionCode": "WR"}, {"name": "AHEJ5L_PSS8_KPS3_HS", "poolingStationName": "Khavda Pooling 2", "regionCode": "WR"}, {"name": "ARE3L_PSS8_KPS3_HS", "poolingStationName": "Khavda Pooling 2", "regionCode": "WR"}, {"name": "ASEJ6PL_PSS8_KPS3_HS", "poolingStationName": "Khavda Pooling 2", "regionCode": "WR"}, {"name": "AGE25CL_PSS8_KPS3_S", "poolingStationName": "Khavda Pooling 2", "regionCode": "WR"}, {"name": "AGE24L_PSS10_KPS3_S", "poolingStationName": "Khavda Pooling 2", "regionCode": "WR"}, {"name": "NTPCREL_PSS1_KPS3_S", "poolingStationName": "Khavda Pooling 2", "regionCode": "WR"}, {"name": "AyanaRP4_DVSR_BHJ_HS", "poolingStationName": "Bhuj Pooling", "regionCode": "WR"}, {"name": "AyanaRP4_ZURA_BHJ_S", "poolingStationName": "Bhuj Pooling", "regionCode": "WR"}, {"name": "CGERP_MORJAR_BHJ2_HS", "poolingStationName": "Bhuj 2 Pooling", "regionCode": "WR"}, {"name": "TeqGreen_Wasi_klm_HS", "poolingStationName": "Kallam", "regionCode": "WR"}, {"name": "AVINC_RMPR_LKD_S", "poolingStationName": "Lakadiya", "regionCode": "WR"}, {"name": "AVGJSUST_RMPR_LKD_S", "poolingStationName": "Lakadiya", "regionCode": "WR"}, {"name": "AVGJLAKA_RMPR_LKD_S", "poolingStationName": "Lakadiya", "regionCode": "WR"}, {"name": "Tuticorin_Mytrah", "poolingStationName": "Tuticorin GIS", "regionCode": "SR"}, {"name": "Tuticorin_BetamWind", "poolingStationName": "Tuticorin GIS", "regionCode": "SR"}, {"name": "Tuticorin_Orange", "poolingStationName": "Tuticorin GIS", "regionCode": "SR"}, {"name": "Tuticorin_GIREL", "poolingStationName": "Tuticorin GIS", "regionCode": "SR"}, {"name": "Tuticorin_JSWRE Two", "poolingStationName": "Tuticorin GIS", "regionCode": "SR"}, {"name": "Tuticorin_JSWRenew_W", "poolingStationName": "Tuticorin GIS", "regionCode": "SR"}, {"name": "PGLR_SREPL", "poolingStationName": "Pugalur", "regionCode": "SR"}, {"name": "PGLR_SAUPL_W", "poolingStationName": "Pugalur", "regionCode": "SR"}, {"name": "HIRIYUR_OSTROKANNADA", "poolingStationName": "HIRIYUR", "regionCode": "SR"}, {"name": "HIRIYUR_ZREPL_W", "poolingStationName": "HIRIYUR", "regionCode": "SR"}, {"name": "KOPPAL_RENEWROSHNI_W", "poolingStationName": "KOPPAL", "regionCode": "SR"}, {"name": "KOPPAL_RenewOjas_W", "poolingStationName": "KOPPAL", "regionCode": "SR"}, {"name": "KOPPAL_AyanaSix_W", "poolingStationName": "KOPPAL", "regionCode": "SR"}, {"name": "KOPPAL_Kleio_W", "poolingStationName": "KOPPAL", "regionCode": "SR"}, {"name": "KOPPAL_SRI1PL_W", "poolingStationName": "KOPPAL", "regionCode": "SR"}, {"name": "GADAG_VENA_W", "poolingStationName": "GADAG", "regionCode": "SR"}, {"name": "GADAG_GreenInfra_W", "poolingStationName": "GADAG", "regionCode": "SR"}, {"name": "GADAG_RSPPL_W", "poolingStationName": "GADAG", "regionCode": "SR"}, {"name": "GADAG_Serentica3_W", "poolingStationName": "GADAG", "regionCode": "SR"}, {"name": "Karur_JSWRETwo_W", "poolingStationName": "Karur", "regionCode": "SR"}, {"name": "Karur_JSWRenew_W", "poolingStationName": "Karur", "regionCode": "SR"}, {"name": "Karur_TPVARDHAMAN_W", "poolingStationName": "Karur", "regionCode": "SR"}, {"name": "Kurnool_AMGreen_W", "poolingStationName": "Kurnool", "regionCode": "SR"}, {"name": "ANP_AthenaBhiwadi", "poolingStationName": "NPKunta", "regionCode": "SR"}, {"name": "ANP_AthenaHisar", "poolingStationName": "NPKunta", "regionCode": "SR"}, {"name": "ANP_AthenaKarnal", "poolingStationName": "NPKunta", "regionCode": "SR"}, {"name": "ANP_Azure", "poolingStationName": "NPKunta", "regionCode": "SR"}, {"name": "ANP_IGS1", "poolingStationName": "NPKunta", "regionCode": "SR"}, {"name": "ANP_IGS2", "poolingStationName": "NPKunta", "regionCode": "SR"}, {"name": "ANP_NTPC", "poolingStationName": "NPKunta", "regionCode": "SR"}, {"name": "ANP_AdaniAPSeven", "poolingStationName": "NPKunta", "regionCode": "SR"}, {"name": "ANP_TataRenewable", "poolingStationName": "NPKunta", "regionCode": "SR"}, {"name": "ANP_AYANA", "poolingStationName": "NPKunta", "regionCode": "SR"}, {"name": "ANP_SprngAgnitra", "poolingStationName": "NPKunta", "regionCode": "SR"}, {"name": "PVG_AMPLUS_TUMKUR", "poolingStationName": "Pavagada", "regionCode": "SR"}, {"name": "PVG_AMPLUS_PAVAGADA", "poolingStationName": "Pavagada", "regionCode": "SR"}, {"name": "PVG_AVAADASolar", "poolingStationName": "Pavagada", "regionCode": "SR"}, {"name": "PVG_AvvadaSolarise", "poolingStationName": "Pavagada", "regionCode": "SR"}, {"name": "PVG_AzurePowerEarth", "poolingStationName": "Pavagada", "regionCode": "SR"}, {"name": "PVG_FORTUM", "poolingStationName": "Pavagada", "regionCode": "SR"}, {"name": "PVG_FortumSolar", "poolingStationName": "Pavagada", "regionCode": "SR"}, {"name": "PVG_KREDL", "poolingStationName": "Pavagada", "regionCode": "SR"}, {"name": "PVG_PARAMPUJYA", "poolingStationName": "Pavagada", "regionCode": "SR"}, {"name": "PVG_ReNew_TN2", "poolingStationName": "Pavagada", "regionCode": "SR"}, {"name": "PVG_AdaniKANine", "poolingStationName": "Pavagada", "regionCode": "SR"}, {"name": "PVG_TATARenewable", "poolingStationName": "Pavagada", "regionCode": "SR"}, {"name": "PVG_Yarrow", "poolingStationName": "Pavagada", "regionCode": "SR"}, {"name": "PVG_ADYAH", "poolingStationName": "Pavagada", "regionCode": "SR"}, {"name": "PVG_IRCON_S", "poolingStationName": "Pavagada", "regionCode": "SR"}, {"name": "Tuticorin_GRTJIPL", "poolingStationName": "Tuticorin GIS", "regionCode": "SR"}, {"name": "Tuticorin_NTPCETPRM", "poolingStationName": "Tuticorin GIS", "regionCode": "SR"}, {"name": "Koppal_SRI1PL", "poolingStationName": "Koppal", "regionCode": "SR"}, {"name": "KOPPAL_RenewOjas_S", "poolingStationName": "Koppal", "regionCode": "SR"}, {"name": "KOPPAL_Kleio_S", "poolingStationName": "Koppal", "regionCode": "SR"}, {"name": "KOPPAL_TPSAURYA_S", "poolingStationName": "Koppal", "regionCode": "SR"}, {"name": "GADAG_VENA_S", "poolingStationName": "Gadag", "regionCode": "SR"}, {"name": "GADAG_Serentica3_S", "poolingStationName": "Gadag", "regionCode": "SR"}, {"name": "KURNOOL_AMGREEN_S", "poolingStationName": "Kurnool", "regionCode": "SR"}, {"name": "Kurnool_Greenko_S", "poolingStationName": "Kurnool", "regionCode": "SR"}, {"name": "KURNOOL 3_SAEL1_S", "poolingStationName": "Kurnool3", "regionCode": "SR"}, {"name": "Kurnool3_SAEL2_S", "poolingStationName": "Kurnool4", "regionCode": "SR"}]